pyconverters_ocrmypdf/__init__.py
pyconverters_ocrmypdf/ocrmypdf.py
pyconverters_ocrmypdf-0.5.107.dist-info/entry_points.txt
pyconverters_ocrmypdf-0.5.107.dist-info/LICENSE
pyconverters_ocrmypdf-0.5.107.dist-info/WHEEL
pyconverters_ocrmypdf-0.5.107.dist-info/METADATA
pyconverters_ocrmypdf-0.5.107.dist-info/RECORD
